tab_pal/__init__.py
tab_pal/tab_pal.py
tab_pal/tabpal.tcss
tab_pal-0.1.1.dist-info/LICENSE
tab_pal-0.1.1.dist-info/METADATA
tab_pal-0.1.1.dist-info/WHEEL
tab_pal-0.1.1.dist-info/entry_points.txt
tab_pal-0.1.1.dist-info/top_level.txt
tab_pal-0.1.1.dist-info/RECORD
