Metadata-Version: 2.1
Name: tab-pal
Version: 0.1.1
Summary: A TUI for adding and editing Tableau custom colour palettes.
Author-email: Ben Nour <hello@ben-nour.com>
License: MIT License
Project-URL: homepage, https://github.com/ben-n93/tab-pal
Project-URL: repository, https://github.com/ben-n93/tab-pal
Classifier: License :: OSI Approved :: MIT License
Classifier: Programming Language :: Python :: 3
Classifier: Programming Language :: Python :: 3.8
Classifier: Programming Language :: Python :: 3.9
Classifier: Programming Language :: Python :: 3.10
Classifier: Programming Language :: Python :: 3.11
Classifier: Programming Language :: Python :: 3.12
Requires-Python: >=3.8
License-File: LICENSE
Requires-Dist: textual==0.81.0
